README.md
setup.py
orfium_oauth_provider/__init__.py
orfium_oauth_provider/adapters.py
orfium_oauth_provider/middlewares.py
orfium_oauth_provider/models.py
orfium_oauth_provider/provider.py
orfium_oauth_provider/tests.py
orfium_oauth_provider/urls.py
orfium_oauth_provider/views.py
orfium_oauth_provider.egg-info/PKG-INFO
orfium_oauth_provider.egg-info/SOURCES.txt
orfium_oauth_provider.egg-info/dependency_links.txt
orfium_oauth_provider.egg-info/requires.txt
orfium_oauth_provider.egg-info/top_level.txt