Metadata-Version: 1.0
Name: orfium-oauth-provider
Version: 0.1.2
Summary: A django-allauth provider for the Orfium.com music platform.
Home-page: https://bitbucket.org/hexacorp-ltd/orfium_oauth_provider
Author: Dimitris Papaspyros
Author-email: dimitris@orfium.com
License: LICENSE
Platform: UNKNOWN
